scilpy/__init__.py
scilpy/version.py
scilpy/cli/__init__.py
scilpy/cli/scil_NODDI_maps.py
scilpy/cli/scil_NODDI_priors.py
scilpy/cli/scil_aodf_metrics.py
scilpy/cli/scil_bids_validate.py
scilpy/cli/scil_bingham_metrics.py
scilpy/cli/scil_btensor_metrics.py
scilpy/cli/scil_bundle_alter_to_target_dice.py
scilpy/cli/scil_bundle_clean_qbx_clusters.py
scilpy/cli/scil_bundle_compute_centroid.py
scilpy/cli/scil_bundle_compute_endpoints_map.py
scilpy/cli/scil_bundle_diameter.py
scilpy/cli/scil_bundle_explore_bundleseg.py
scilpy/cli/scil_bundle_filter_by_occurrence.py
scilpy/cli/scil_bundle_fixel_analysis.py
scilpy/cli/scil_bundle_generate_priors.py
scilpy/cli/scil_bundle_label_map.py
scilpy/cli/scil_bundle_mean_fixel_afd.py
scilpy/cli/scil_bundle_mean_fixel_afd_from_hdf5.py
scilpy/cli/scil_bundle_mean_fixel_bingham_metric.py
scilpy/cli/scil_bundle_mean_fixel_mrds_metric.py
scilpy/cli/scil_bundle_mean_std.py
scilpy/cli/scil_bundle_pairwise_comparison.py
scilpy/cli/scil_bundle_reject_outliers.py
scilpy/cli/scil_bundle_score_many_bundles_one_tractogram.py
scilpy/cli/scil_bundle_score_same_bundle_many_segmentations.py
scilpy/cli/scil_bundle_shape_measures.py
scilpy/cli/scil_bundle_uniformize_endpoints.py
scilpy/cli/scil_bundle_volume_per_label.py
scilpy/cli/scil_connectivity_compare_populations.py
scilpy/cli/scil_connectivity_compute_matrices.py
scilpy/cli/scil_connectivity_compute_pca.py
scilpy/cli/scil_connectivity_compute_simple_matrix.py
scilpy/cli/scil_connectivity_filter.py
scilpy/cli/scil_connectivity_graph_measures.py
scilpy/cli/scil_connectivity_hdf5_average_density_map.py
scilpy/cli/scil_connectivity_math.py
scilpy/cli/scil_connectivity_normalize.py
scilpy/cli/scil_connectivity_pairwise_agreement.py
scilpy/cli/scil_connectivity_print_filenames.py
scilpy/cli/scil_connectivity_reorder_rois.py
scilpy/cli/scil_data_download.py
scilpy/cli/scil_denoising_nlmeans.py
scilpy/cli/scil_dki_metrics.py
scilpy-2.2.0.dist-info/METADATA
scilpy-2.2.0.dist-info/WHEEL
scilpy-2.2.0.dist-info/entry_points.txt
scilpy-2.2.0.dist-info/top_level.txt
scilpy-2.2.0.dist-info/RECORD
scilpy-2.2.0.dist-info/licenses/LICENSE
