Metadata-Version: 2.4
Name: scilpy
Version: 2.2.0
Summary: Scilpy: diffusion MRI tools and utilities
Author: SCIL Team
Classifier: Development Status :: 3 - Alpha
Classifier: Environment :: Console
Classifier: Intended Audience :: Science/Research
Classifier: Operating System :: OS Independent
Classifier: Programming Language :: Python
Classifier: Topic :: Scientific/Engineering
Requires-Python: <3.13,>=3.10
License-File: LICENSE
Requires-Dist: bctpy==0.6.*
Requires-Dist: bids-validator==1.14.*
Requires-Dist: bz2file==0.98
Requires-Dist: coloredlogs==15.0.*
Requires-Dist: cvxpy==1.6.*
Requires-Dist: cycler==0.12.*
Requires-Dist: deepdiff<8.7,>=8.1
Requires-Dist: dipy==1.11.*
Requires-Dist: dmri-amico==2.1.*
Requires-Dist: dmri-commit==2.3.*
Requires-Dist: docopt==0.6.*
Requires-Dist: dvc==3.59.*
Requires-Dist: formulaic==0.5.*
Requires-Dist: fury==0.12.*
Requires-Dist: future==1.0.*
Requires-Dist: GitPython==3.1.*
Requires-Dist: h5py==3.12.*
Requires-Dist: joblib==1.4.*
Requires-Dist: kiwisolver==1.4.*
Requires-Dist: matplotlib==3.10.*
Requires-Dist: nibabel==5.3.*
Requires-Dist: nilearn==0.11.*
Requires-Dist: nltk==3.9.*
Requires-Dist: numba==0.61.*
Requires-Dist: numba-kdtree==0.4.*
Requires-Dist: numpy==1.26.*
Requires-Dist: openpyxl==3.1.*
Requires-Dist: packaging==24.*
Requires-Dist: pybids==0.18.*
Requires-Dist: PyMCubes==0.1.*
Requires-Dist: pyparsing==3.2.*
Requires-Dist: PySocks==1.7.*
Requires-Dist: pytest==8.3.*
Requires-Dist: pytest-xdist==3.8.*
Requires-Dist: pytest-console-scripts==1.4.*
Requires-Dist: pytest-cov==6.0.*
Requires-Dist: pytest-html==4.1.*
Requires-Dist: pytest-metadata==3.1.*
Requires-Dist: pytest-mock==3.14.*
Requires-Dist: python-dateutil==2.9.*
Requires-Dist: pytz==2024.2
Requires-Dist: requests==2.32.*
Requires-Dist: scikit-image==0.25.*
Requires-Dist: scikit-learn==1.6.*
Requires-Dist: scipy==1.15.*
Requires-Dist: six==1.17.*
Requires-Dist: statsmodels==0.14.*
Requires-Dist: trimeshpy==0.0.*
Requires-Dist: vtk==9.3.*
Provides-Extra: dev
Requires-Dist: pytest; extra == "dev"
Requires-Dist: ipython; extra == "dev"
Dynamic: license-file
